Metadata-Version: 2.1
Name: pro0video-ferramentas
Version: 1.0
Summary: Este pacote irá fornecer ferramentas de processamento de vídeo
Author: Matheus
Author-email: matheusferrazo_@hotmail.com
Keywords: camera,,video,processamento
License-File: license.txt
